eurostatpy/EuroStatPy.py
eurostatpy/__init__.py
eurostatpy/utilities.py
eurostatpy/jsonstatpy/__init__.py
eurostatpy/jsonstatpy/collection.py
eurostatpy/jsonstatpy/dataset.py
eurostatpy/jsonstatpy/dimension.py
eurostatpy/jsonstatpy/exceptions.py
eurostatpy/jsonstatpy/schemas.py
eurostatpy/jsonstatpy/utility.py
eurostatpy/jsonstatpy/value.py
eurostatpy/schema/table_of_contents.xml
eurostatpy-1.1.0.dist-info/LICENSE
eurostatpy-1.1.0.dist-info/METADATA
eurostatpy-1.1.0.dist-info/WHEEL
eurostatpy-1.1.0.dist-info/top_level.txt
eurostatpy-1.1.0.dist-info/RECORD
