Metadata-Version: 2.1
Name: eurostatpy
Version: 1.1.0
Summary: Basic package for querying & downloading EuroStat data by dataset name or ID.
License-File: LICENSE
Requires-Dist: pandas
Requires-Dist: terminaltables
Requires-Dist: aiohttp
